negmas_negolog/__init__.py
negmas_negolog/agents/__init__.py
negmas_negolog/agents/agent_buyog.py
negmas_negolog/agents/agent_gg.py
negmas_negolog/agents/agent_kn.py
negmas_negolog/agents/ahbune.py
negmas_negolog/agents/atlas3.py
negmas_negolog/agents/boulware.py
negmas_negolog/agents/caduceus.py
negmas_negolog/agents/caduceus2015.py
negmas_negolog/agents/conceder.py
negmas_negolog/agents/cuhk.py
negmas_negolog/agents/hardheaded.py
negmas_negolog/agents/hybrid.py
negmas_negolog/agents/iamhaggler.py
negmas_negolog/agents/kawaii.py
negmas_negolog/agents/linear.py
negmas_negolog/agents/lucky2022.py
negmas_negolog/agents/micro.py
negmas_negolog/agents/nice_tit_for_tat.py
negmas_negolog/agents/pars.py
negmas_negolog/agents/parscat.py
negmas_negolog/agents/ponpoko.py
negmas_negolog/agents/random_dance.py
negmas_negolog/agents/rubick.py
negmas_negolog/agents/saga.py
negmas_negolog/agents/yx.py
negmas_negolog/common.py
negmas_negolog/py.typed
negmas_negolog/registry_init.py
negmas_negolog-0.2.3.dist-info/WHEEL
negmas_negolog-0.2.3.dist-info/METADATA
negmas_negolog-0.2.3.dist-info/RECORD
