Metadata-Version: 2.3
Name: negmas-negolog
Version: 0.2.3
Summary: NegMAS wrappers for NegoLog negotiating agents
Author: Yasser Mohammad
Author-email: Yasser Mohammad <yasserfarouk@gmail.com>
Requires-Dist: negmas>=0.14.0
Requires-Dist: numpy>=1.24.0
Requires-Dist: scipy>=1.10.0
Requires-Dist: pandas>=2.0.0
Requires-Dist: matplotlib>=3.7.0
Requires-Dist: pyyaml>=6.0
Requires-Dist: plotly>=5.18.0
Requires-Dist: seaborn>=0.13.0
Requires-Dist: scikit-learn>=1.4.0
Requires-Dist: openpyxl>=3.1.0
Requires-Dist: numba>=0.58.0
Requires-Dist: pytest>=7.0.0 ; extra == 'dev'
Requires-Dist: pytest-cov>=4.0.0 ; extra == 'dev'
Requires-Python: >=3.10
Provides-Extra: dev
